{"id":"82","type":"Group","name":"barthel","text":"Barthel","items":[{"id":"767","type":"QuestionSelect","text":"Alimentazione","options":{"required":true},"selectOptions":[{"text":"Indipendente","score":10},{"text":"Necessita di aiuto","score":5},{"text":"Dipendente (deve essere imboccato o alimentato)","score":0}]},{"id":"768","type":"QuestionSelect","text":"Bagno-Doccia","options":{"required":true},"selectOptions":[{"text":"Indipendente","score":10},{"text":"Necessita di aiuto","score":5},{"text":"Dipendente","score":0}]},{"id":"769","type":"QuestionSelect","text":"Igiene Personale","options":{"required":true},"selectOptions":[{"text":"Indipendente","score":10},{"text":"Necessita di aiuto","score":5},{"text":"Dipendente (sostituzione, aiuto, supervisione) ","score":0}]},{"id":"770","type":"QuestionSelect","text":"Vestirsi","options":{"required":true},"selectOptions":[{"text":"Indipendente","score":10},{"text":"Necessita di aiuto","score":5},{"text":"Dipendente","score":0}]},{"id":"771","type":"QuestionSelect","text":"Continenza Intestinale","options":{"required":true},"selectOptions":[{"text":"Continente, autonomo nell’uso di clisteri","score":10},{"text":"Occasionale incontinenza, aiuto per clisteri","score":5},{"text":"Incontinente ","score":0}]},{"id":"772","type":"QuestionSelect","text":"Continenza Urinaria","options":{"required":true},"selectOptions":[{"text":"Continente, gestione autonoma di dispositivo esterno","score":10},{"text":"Occasionale incontinenza, aiuto per dispositivo esterno","score":5},{"text":"Incontinente","score":0}]},{"id":"773","type":"QuestionSelect","text":"Uso WC","options":{"required":true},"selectOptions":[{"text":"Indipendente (per uso WC o padella)","score":10},{"text":"Necessita di aiuto","score":5},{"text":"Dipendente","score":0}]},{"id":"774","type":"QuestionSelect","text":"Trasferimenti Letto-Sedia-Carrozzina","options":{"required":true},"selectOptions":[{"text":"Indipendente","score":15},{"text":"Necessita di aiuto o supervisione","score":10},{"text":"In grado di sedersi ma richiede assistenza per trasferirsi","score":5},{"text":"Incapace (non equilibrio da seduto)","score":0}]},{"id":"775","type":"QuestionSelect","text":"Deambulazione","options":{"required":true},"selectOptions":[{"text":"Indipendente (può usare ausili)","score":15},{"text":"Necessita di aiuto di una persona","score":10},{"text":"Indipendente con carrozzina","score":5},{"text":"Non deambula","score":0}]},{"id":"776","type":"QuestionSelect","text":"Fare le scale","options":{"required":true},"selectOptions":[{"text":"Indipendente (può usare ausili)","score":10},{"text":"Necessita di aiuto di una persona","score":5},{"text":"Incapace","score":0}]},{"id":"778","type":"Fn","text":"SCORE","layout":{"style":"score"},"parameters":["767","768","769","770","771","772","773","774","775","776"],"fnCompute":"sum"}],"layout":{"style":"card"},"description":""}
